[
    {
        "title": "Blockvote",
        "description": "A POC polling app on the Polygon chain",
        "link": "https://github.com/CodeWithShreyans/Blockvote-solidity",
        "tag": "archived"
    },
    {
        "title": "Duelance",
        "description": "My first startup, a revolutionary freelancer marketplace",
        "link": "https://github.com/duelance-app",
        "tag": "archived"
    },
    {
        "title": "The AI Chronicles",
        "description": "A newsletter, curated by AI",
        "link": "https://github.com/CodeWithShreyans/theaichronicles",
        "tag": "archived"
    },
    {
        "title": "Findy Thingy",
        "description": "Search your emails with AI",
        "link": "https://github.com/CodeWithShreyans/findy-thingy",
        "tag": "archived"
    },
    {
        "title": "Water Quality Tester",
        "description": "Custom designed printed circuit board to test water quality",
        "link": "https://github.com/CodeWithShreyans/trail-water-tester"
    },
    {
        "title": "upstash-kv",
        "description": "Simple Upstash Redish client based on Vercel KV",
        "link": "https://www.npmjs.com/package/upstash-kv"
    },
    {
        "title": "shreyans.sh",
        "description": "This website, my personal corner of the web",
        "link": "https://shreyans.sh"
    },
    {
        "title": "Evently",
        "description": "Complete event manager for students",
        "link": "https://eventlyhq.com"
    },
    {
        "title": "Guider",
        "description": "Offline access to crucial emergency guides",
        "link": "https://useguider.com",
        "tag": "pre-release"
    }
]
